biwoco/__init__.py
biwoco/services.py
biwoco-0.0.2.dist-info/LICENSE
biwoco-0.0.2.dist-info/METADATA
biwoco-0.0.2.dist-info/WHEEL
biwoco-0.0.2.dist-info/top_level.txt
biwoco-0.0.2.dist-info/RECORD
