Metadata-Version: 2.1
Name: biwoco
Version: 0.0.2
Summary: A sample python package
Home-page: https://github.com/dnt-austion/biwoco
Author: Thanh Dao
Author-email: dnthanh090108@gmail.com
Requires-Python: >=3.10
License-File: LICENSE
Requires-Dist: requests
